{
  "updated_at": "2026-02-08T04:24:38.080401",
  "all_time_stats": {
    "total_combined_volume": 675606854.65,
    "total_spot_volume": 126982894.01,
    "total_futures_volume": 548623960.64,
    "top_5_spot": [
      {
        "pair": "BTC/USDC",
        "volume": 13159771.51
      },
      {
        "pair": "ETH/USDC",
        "volume": 12244087.52
      },
      {
        "pair": "SOL/USDC",
        "volume": 11689536.16
      },
      {
        "pair": "MAG7ssi/USDC",
        "volume": 10665268.88
      },
      {
        "pair": "LINK/USDC",
        "volume": 10489860.71
      }
    ],
    "top_5_futures": [
      {
        "pair": "BTC-USD",
        "volume": 181632686.11
      },
      {
        "pair": "SOL-USD",
        "volume": 49822240.7
      },
      {
        "pair": "ETH-USD",
        "volume": 49654617.64
      },
      {
        "pair": "XAUT-USD",
        "volume": 24770925.7
      },
      {
        "pair": "DOGE-USD",
        "volume": 15890695.68
      }
    ]
  },
  "today_stats": {
    "date": "2026-02-08",
    "top_5_spot": [
      {
        "pair": "BTC/USDC",
        "volume": 43345.0
      },
      {
        "pair": "ETH/USDC",
        "volume": 38795.65
      },
      {
        "pair": "MAG7ssi/USDC",
        "volume": 33397.58
      },
      {
        "pair": "XAUT/USDC",
        "volume": 30362.49
      },
      {
        "pair": "SOSO/USDC",
        "volume": 13020.43
      }
    ],
    "top_5_futures": [
      {
        "pair": "BTC-USD",
        "volume": 2112460.99
      },
      {
        "pair": "XAUT-USD",
        "volume": 923078.88
      },
      {
        "pair": "ETH-USD",
        "volume": 160370.5
      },
      {
        "pair": "SOL-USD",
        "volume": 117285.98
      },
      {
        "pair": "HYPE-USD",
        "volume": 31468.1
      }
    ]
  }
}