{
  "updated_at": "2026-02-13T14:33:56.398035",
  "all_time_stats": {
    "total_combined_volume": 845283088.15,
    "total_spot_volume": 139091440.95,
    "total_futures_volume": 706191647.2,
    "top_5_spot": [
      {
        "pair": "BTC/USDC",
        "volume": 17437461.39
      },
      {
        "pair": "ETH/USDC",
        "volume": 13265768.11
      },
      {
        "pair": "SOL/USDC",
        "volume": 12256539.52
      },
      {
        "pair": "SOSO/USDC",
        "volume": 11926667.11
      },
      {
        "pair": "MAG7ssi/USDC",
        "volume": 11243063.58
      }
    ],
    "top_5_futures": [
      {
        "pair": "BTC-USD",
        "volume": 272742900.07
      },
      {
        "pair": "ETH-USD",
        "volume": 58782642.46
      },
      {
        "pair": "SOL-USD",
        "volume": 55308510.69
      },
      {
        "pair": "XAUT-USD",
        "volume": 45752831.27
      },
      {
        "pair": "DOGE-USD",
        "volume": 16565645.43
      }
    ]
  },
  "today_stats": {
    "date": "2026-02-13",
    "top_5_spot": [
      {
        "pair": "BTC/USDC",
        "volume": 1623911.53
      },
      {
        "pair": "SOSO/USDC",
        "volume": 545593.48
      },
      {
        "pair": "ETH/USDC",
        "volume": 246568.4
      },
      {
        "pair": "SOL/USDC",
        "volume": 205127.77
      },
      {
        "pair": "XAUT/USDC",
        "volume": 127735.61
      }
    ],
    "top_5_futures": [
      {
        "pair": "BTC-USD",
        "volume": 19340788.12
      },
      {
        "pair": "XAUT-USD",
        "volume": 3797648.99
      },
      {
        "pair": "ETH-USD",
        "volume": 1413444.39
      },
      {
        "pair": "SOL-USD",
        "volume": 741851.57
      },
      {
        "pair": "HYPE-USD",
        "volume": 246657.8
      }
    ]
  }
}