{
  "updated_at": "2026-02-15T09:20:15.583886",
  "all_time_stats": {
    "total_combined_volume": 933468038.13,
    "total_spot_volume": 144479065.09,
    "total_futures_volume": 788988973.04,
    "top_5_spot": [
      {
        "pair": "BTC/USDC",
        "volume": 18969256.57
      },
      {
        "pair": "ETH/USDC",
        "volume": 14248806.88
      },
      {
        "pair": "SOSO/USDC",
        "volume": 12895703.54
      },
      {
        "pair": "SOL/USDC",
        "volume": 12497340.78
      },
      {
        "pair": "MAG7ssi/USDC",
        "volume": 11376877.97
      }
    ],
    "top_5_futures": [
      {
        "pair": "BTC-USD",
        "volume": 320339004.47
      },
      {
        "pair": "ETH-USD",
        "volume": 64977178.48
      },
      {
        "pair": "XAUT-USD",
        "volume": 60367262.53
      },
      {
        "pair": "SOL-USD",
        "volume": 59194189.11
      },
      {
        "pair": "DOGE-USD",
        "volume": 16815156.2
      }
    ]
  },
  "today_stats": {
    "date": "2026-02-15",
    "top_5_spot": [
      {
        "pair": "BTC/USDC",
        "volume": 201379.16
      },
      {
        "pair": "SOSO/USDC",
        "volume": 158129.72
      },
      {
        "pair": "XAUT/USDC",
        "volume": 85588.23
      },
      {
        "pair": "ETH/USDC",
        "volume": 79400.58
      },
      {
        "pair": "SOL/USDC",
        "volume": 21235.47
      }
    ],
    "top_5_futures": [
      {
        "pair": "BTC-USD",
        "volume": 6210504.68
      },
      {
        "pair": "ETH-USD",
        "volume": 743763.49
      },
      {
        "pair": "SOL-USD",
        "volume": 442129.57
      },
      {
        "pair": "XAUT-USD",
        "volume": 343065.69
      },
      {
        "pair": "HYPE-USD",
        "volume": 113505.03
      }
    ]
  }
}