{
  "updated_at": "2026-02-11T11:35:57.189588",
  "all_time_stats": {
    "total_combined_volume": 758201808.83,
    "total_spot_volume": 132678416.08,
    "total_futures_volume": 625523392.75,
    "top_5_spot": [
      {
        "pair": "BTC/USDC",
        "volume": 14681502.58
      },
      {
        "pair": "ETH/USDC",
        "volume": 12761588.84
      },
      {
        "pair": "SOL/USDC",
        "volume": 11953441.65
      },
      {
        "pair": "MAG7ssi/USDC",
        "volume": 11074628.44
      },
      {
        "pair": "SOSO/USDC",
        "volume": 10972149.18
      }
    ],
    "top_5_futures": [
      {
        "pair": "BTC-USD",
        "volume": 224633295.44
      },
      {
        "pair": "ETH-USD",
        "volume": 53900353.73
      },
      {
        "pair": "SOL-USD",
        "volume": 52470311.87
      },
      {
        "pair": "XAUT-USD",
        "volume": 34073267.16
      },
      {
        "pair": "DOGE-USD",
        "volume": 16336874.53
      }
    ]
  },
  "today_stats": {
    "date": "2026-02-11",
    "top_5_spot": [
      {
        "pair": "BTC/USDC",
        "volume": 175169.71
      },
      {
        "pair": "SOL/USDC",
        "volume": 107654.43
      },
      {
        "pair": "SOSO/USDC",
        "volume": 106760.03
      },
      {
        "pair": "MAG7ssi/USDC",
        "volume": 55337.34
      },
      {
        "pair": "BNB/USDC",
        "volume": 37309.67
      }
    ],
    "top_5_futures": [
      {
        "pair": "BTC-USD",
        "volume": 5191846.06
      },
      {
        "pair": "XAUT-USD",
        "volume": 935151.68
      },
      {
        "pair": "ETH-USD",
        "volume": 798738.56
      },
      {
        "pair": "SOL-USD",
        "volume": 263259.68
      },
      {
        "pair": "SUI-USD",
        "volume": 135661.79
      }
    ]
  }
}